learndl/__init__.py
learndl/decorators.py
learndl/models.py
learndl/utils.py
learndl/layers/__init__.py
learndl/layers/cost.py
learndl/layers/dense.py
learndl/layers/input.py
learndl/layers/layer.py
learndl/math/__init__.py
learndl/math/activations.py
learndl/math/losses.py
learndl/math/metricers.py
learndl/math/optimizers.py
learndl-0.6.3.dist-info/LICENSE
learndl-0.6.3.dist-info/METADATA
learndl-0.6.3.dist-info/WHEEL
learndl-0.6.3.dist-info/top_level.txt
learndl-0.6.3.dist-info/RECORD
