Metadata-Version: 2.1
Name: learndl
Version: 0.6.3
Summary: Deep Learning for beginners
Home-page: https://github.com/mrcorecoder/learndl
Author: indeep
Author-email: qianshuai2018@aliyun.com
License: UNKNOWN
Platform: UNKNOWN
Classifier: Programming Language :: Python :: 3
Classifier: License :: OSI Approved :: Apache Software License
Classifier: Operating System :: OS Independent
